{"title":"Body","body":{"description":"","content":{"application/json-patch+json":{"schema":{"allOf":[{"required":["lang_code","user_id","version_number"],"type":"object","properties":{"version_number":{"type":"integer","description":"The version number of the article to be forked","format":"int32"},"user_id":{"minLength":1,"type":"string","description":"The ID of the team account that will be marked as the contributor of this fork"},"lang_code":{"minLength":1,"type":"string","description":"Language code of the article"}},"additionalProperties":false,"title":"ForkArticleVersionRequest"}]},"examples":{"Non-Empty body is required.":{"summary":"This response is due to an empty request body. \\n Kindly make some body parameters to get success response.","value":{"version_number":2,"user_id":"f11efc6f-e968-4e95-82eb-85ad61559de8","lang_code":"en"}}}},"application/json":{"schema":{"allOf":[{"required":["lang_code","user_id","version_number"],"type":"object","properties":{"version_number":{"type":"integer","description":"The version number of the article to be forked","format":"int32"},"user_id":{"minLength":1,"type":"string","description":"The ID of the team account that will be marked as the contributor of this fork"},"lang_code":{"minLength":1,"type":"string","description":"Language code of the article"}},"additionalProperties":false,"title":"ForkArticleVersionRequest"}]},"examples":{"Non-Empty body is required.":{"summary":"This response is due to an empty request body. \\n Kindly make some body parameters to get success response.","value":{"version_number":2,"user_id":"f11efc6f-e968-4e95-82eb-85ad61559de8","lang_code":"en"}}}},"text/json":{"schema":{"allOf":[{"required":["lang_code","user_id","version_number"],"type":"object","properties":{"version_number":{"type":"integer","description":"The version number of the article to be forked","format":"int32"},"user_id":{"minLength":1,"type":"string","description":"The ID of the team account that will be marked as the contributor of this fork"},"lang_code":{"minLength":1,"type":"string","description":"Language code of the article"}},"additionalProperties":false,"title":"ForkArticleVersionRequest"}]},"examples":{"Non-Empty body is required.":{"summary":"This response is due to an empty request body. \\n Kindly make some body parameters to get success response.","value":{"version_number":2,"user_id":"f11efc6f-e968-4e95-82eb-85ad61559de8","lang_code":"en"}}}},"application/*+json":{"schema":{"allOf":[{"required":["lang_code","user_id","version_number"],"type":"object","properties":{"version_number":{"type":"integer","description":"The version number of the article to be forked","format":"int32"},"user_id":{"minLength":1,"type":"string","description":"The ID of the team account that will be marked as the contributor of this fork"},"lang_code":{"minLength":1,"type":"string","description":"Language code of the article"}},"additionalProperties":false,"title":"ForkArticleVersionRequest"}]},"examples":{"Non-Empty body is required.":{"summary":"This response is due to an empty request body. \\n Kindly make some body parameters to get success response.","value":{"version_number":2,"user_id":"f11efc6f-e968-4e95-82eb-85ad61559de8","lang_code":"en"}}}}}}}